{
   "parameters" : [
      {
         "value" : "",
         "desc" : "绑定属性,根据类目确定绑定属性是否是必须",
         "name" : "binds",
         "type" : "text",
         "classname" : ""
      },
      {
         "value" : "",
         "desc" : "类目ID",
         "name" : "cid",
         "type" : "text",
         "classname" : "isMust"
      },
      {
         "value" : "",
         "desc" : "用户自定义属性，1636953:DDFAFAEED",
         "name" : "customer_props",
         "type" : "text",
         "classname" : ""
      },
      {
         "value" : "",
         "desc" : "产品描述",
         "name" : "desc",
         "type" : "text",
         "classname" : ""
      },
      {
         "value" : "",
         "desc" : "产品主图，要先上传图片后再提交测试，否则产品图片不会被提交",
         "name" : "image",
         "type" : "file",
         "classname" : "isMust"
      },
      {
         "value" : "",
         "desc" : "产品名称",
         "name" : "name",
         "type" : "text",
         "classname" : "isMust"
      },
      {
         "value" : "",
         "desc" : "外部产品ID",
         "name" : "outer_id",
         "type" : "text",
         "classname" : ""
      },
      {
         "value" : "",
         "desc" : "产品市场价",
         "name" : "price",
         "type" : "text",
         "classname" : "isMust"
      },
      {
         "value" : "",
         "desc" : "关键属性pid:vid;pid:vid ,如果碰到用户自定义属性，请用customer_props",
         "name" : "props",
         "type" : "text",
         "classname" : ""
      },
      {
         "value" : "",
         "desc" : "销售属性",
         "name" : "sale_props",
         "type" : "text",
         "classname" : ""
      },
      {
         "value" : "",
         "desc" : "商家编码",
         "name" : "tsc",
         "type" : "text",
         "classname" : ""
      }
   ],
   "api_type" : "Product",
   "class" : "Net_Top_Request_ProductAdd",
   "method" : "taobao.product.add",
   "is_secure" : "1"
}