{
   "parameters" : [
      {
         "value" : "",
         "desc" : "需要返回的字段",
         "name" : "fields",
         "type" : "text",
         "classname" : "isMust"
      },
      {
         "value" : "",
         "desc" : "退款单号",
         "name" : "refund_id",
         "type" : "text",
         "classname" : "isMust"
      }
   ],
   "fields" : {
      ":all" : [
         "refund_id",
         "alipay_no",
         "tid",
         "oid",
         "buyer_nick",
         "seller_nick",
         "total_fee",
         "status",
         "created",
         "refund_fee",
         "good_status",
         "has_good_return",
         "payment",
         "reason",
         "desc",
         "iid",
         "title",
         "price",
         "num",
         "good_return_time",
         "company_name",
         "sid",
         "address"
      ]
   },
   "api_type" : "Trade",
   "class" : "Net_Top_Request_RefundGet",
   "method" : "taobao.refund.get",
   "is_secure" : "1"
}